MANIFEST.in
README.md
setup.py
nbextension_share_button.egg-info/PKG-INFO
nbextension_share_button.egg-info/SOURCES.txt
nbextension_share_button.egg-info/dependency_links.txt
nbextension_share_button.egg-info/top_level.txt
share_button/__init__.py
share_button/static/main.js
share_button/static/popup.js
share_button/static/share-popup.css