Metadata-Version: 1.0
Name: nbextension-share-button
Version: 0.1.8
Summary: A Jupyter Notebook extension that adds a share button to the toolbar.
Home-page: https://github.com/globocom/nbextension-share-button/
Author: Globo.com
Author-email: UNKNOWN
License: UNKNOWN
Keywords: nbextension,share,notebook
Platform: UNKNOWN
